Yolov4Detector/Yolov4Detector.py
Yolov4Detector/__init__.py
Yolov4Detector/darknet.py
Yolov4Detector/darknet_batchimages.py
Yolov4Detector/darknet_images.py
Yolov4Detector/darknet_video.py
Yolov4Detector/io.py
Yolov4Detector/utils.py
Yolov4Detector/cfgs/yolov4_tiny/coco.names
Yolov4Detector/cfgs/yolov4_tiny/yolov4-tiny.cfg
Yolov4Detector/cfgs/yolov4_tiny/yolov4-tiny.weights
Yolov4Detector/samples/bus.jpg
Yolov4Detector/samples/zidane.jpg
Yolov4Detector-0.1.2.dist-info/LICENSE
Yolov4Detector-0.1.2.dist-info/METADATA
Yolov4Detector-0.1.2.dist-info/WHEEL
Yolov4Detector-0.1.2.dist-info/top_level.txt
Yolov4Detector-0.1.2.dist-info/RECORD
