Metadata-Version: 2.1
Name: Yolov4Detector
Version: 0.1.2
Summary: Yolov4Detector
Home-page: https://github.com/GoatWang/Yolov4Detector
Author: GoatWang
Author-email: jeremy4555@yahoo.com.tw
License: UNKNOWN
Platform: UNKNOWN
Classifier: Programming Language :: Python :: 3
Classifier: License :: OSI Approved :: MIT License
Classifier: Operating System :: OS Independent
Requires-Dist: numpy (>=1.17)
Requires-Dist: opencv-python (>=4.1)
Requires-Dist: matplotlib
Requires-Dist: pillow
